{
  "theater": {
    "chain": "toho",
    "name": "TOHOシネマズ新宿",
    "area": "新宿",
    "prefecture": "東京都",
    "url": "https://www.tohotheater.jp/net/schedule/076/TNPI2000J01.do"
  },
  "date": "2026-05-16",
  "movies": [
    {
      "title": "僕のヒーローアカデミア　Ｔｈｅ　Ａｎｉｍａｔｉｏｎ　１０ｔｈ",
      "duration_min": 115,
      "screenings": [
        {
          "start_time": "13:00",
          "end_time": "15:00",
          "screen": "SCREEN4",
          "format": "2D",
          "language": "日本語",
          "availability": "unknown"
        }
      ]
    }
  ],
  "scraped_at": "2026-05-10T11:32:51.592012"
}