{
  "theater": {
    "chain": "109cinemas",
    "name": "109シネマズ二子玉川",
    "area": "二子玉川",
    "prefecture": "東京都",
    "url": "https://109cinemas.net/futakotamagawa/"
  },
  "date": "2026-07-12",
  "movies": [
    {
      "title": "ちゃんみな AREA OF DIAMOND…[ODS]",
      "duration_min": 150,
      "screenings": [
        {
          "start_time": "18:00",
          "end_time": "21:00",
          "screen": "シアター5",
          "format": "2D",
          "language": "日本語",
          "availability": "available"
        }
      ]
    }
  ],
  "scraped_at": "2026-07-06T10:38:27.482827"
}