{
  "theater": {
    "chain": "tjoy",
    "name": "横浜ブルク13",
    "area": "みなとみらい",
    "prefecture": "神奈川県",
    "url": "https://tjoy.jp/yokohama_burg13"
  },
  "date": "2026-05-12",
  "movies": [
    {
      "title": "コードギアス 奪還のロゼ 第1幕",
      "duration_min": 74,
      "screenings": [
        {
          "start_time": "19:00",
          "end_time": "20:25",
          "screen": "シアター１０",
          "format": "2D",
          "language": "日本語",
          "availability": "unknown"
        }
      ]
    },
    {
      "title": "劇場版「魔法科高校の劣等生 四葉継承編」",
      "duration_min": 103,
      "screenings": [
        {
          "start_time": "11:30",
          "end_time": "13:25",
          "screen": "シアター１１",
          "format": "2D",
          "language": "日本語",
          "availability": "unknown"
        },
        {
          "start_time": "13:45",
          "end_time": "15:40",
          "screen": "シアター１１",
          "format": "2D",
          "language": "日本語",
          "availability": "unknown"
        },
        {
          "start_time": "16:00",
          "end_time": "17:55",
          "screen": "シアター１１",
          "format": "2D",
          "language": "日本語",
          "availability": "unknown"
        },
        {
          "start_time": "19:25",
          "end_time": "21:20",
          "screen": "シアター９",
          "format": "2D",
          "language": "日本語",
          "availability": "unknown"
        },
        {
          "start_time": "21:40",
          "end_time": "23:35",
          "screen": "シアター９",
          "format": "2D",
          "language": "日本語",
          "availability": "unknown"
        }
      ]
    },
    {
      "title": "映画 ラブライブ！蓮ノ空女学院スクールアイドルクラブ Bloom Garden Party",
      "duration_min": 75,
      "screenings": [
        {
          "start_time": "11:00",
          "end_time": "12:25",
          "screen": "シアター９",
          "format": "2D",
          "language": "日本語",
          "availability": "unknown"
        },
        {
          "start_time": "12:45",
          "end_time": "14:10",
          "screen": "シアター９",
          "format": "2D",
          "language": "日本語",
          "availability": "unknown"
        },
        {
          "start_time": "17:30",
          "end_time": "18:55",
          "screen": "シアター２",
          "format": "2D",
          "language": "日本語",
          "availability": "unknown"
        },
        {
          "start_time": "21:25",
          "end_time": "22:50",
          "screen": "シアター１１",
          "format": "2D",
          "language": "日本語",
          "availability": "unknown"
        }
      ]
    },
    {
      "title": "【字幕】グランド・イリュージョン／ダイヤモンド・ミッション",
      "duration_min": 113,
      "screenings": [
        {
          "start_time": "08:50",
          "end_time": "10:55",
          "screen": "シアター４",
          "format": "2D",
          "language": "字幕",
          "availability": "unknown"
        },
        {
          "start_time": "13:25",
          "end_time": "15:30",
          "screen": "シアター３",
          "format": "2D",
          "language": "字幕",
          "availability": "unknown"
        },
        {
          "start_time": "17:00",
          "end_time": "19:05",
          "screen": "シアター９",
          "format": "2D",
          "language": "字幕",
          "availability": "unknown"
        },
        {
          "start_time": "20:50",
          "end_time": "22:55",
          "screen": "シアター３",
          "format": "2D",
          "language": "字幕",
          "availability": "unknown"
        }
      ]
    },
    {
      "title": "【吹替】ひつじ探偵団",
      "duration_min": 109,
      "screenings": [
        {
          "start_time": "11:30",
          "end_time": "13:30",
          "screen": "シアター８",
          "format": "2D",
          "language": "吹替",
          "availability": "unknown"
        },
        {
          "start_time": "16:30",
          "end_time": "18:30",
          "screen": "シアター８",
          "format": "2D",
          "language": "吹替",
          "availability": "unknown"
        },
        {
          "start_time": "21:20",
          "end_time": "23:20",
          "screen": "シアター８",
          "format": "2D",
          "language": "吹替",
          "availability": "unknown"
        }
      ]
    },
    {
      "title": "【字幕】レッド・ソニア／反逆の剣(PG12)",
      "duration_min": 110,
      "screenings": [
        {
          "start_time": "08:45",
          "end_time": "10:45",
          "screen": "シアター１０",
          "format": "2D",
          "language": "字幕",
          "availability": "unknown"
        },
        {
          "start_time": "13:40",
          "end_time": "15:40",
          "screen": "シアター１３",
          "format": "2D",
          "language": "字幕",
          "availability": "unknown"
        },
        {
          "start_time": "21:25",
          "end_time": "23:25",
          "screen": "シアター２",
          "format": "2D",
          "language": "字幕",
          "availability": "unknown"
        }
      ]
    },
    {
      "title": "【字幕】デンジャラス・アニマルズ 絶望海域(PG12)",
      "duration_min": 98,
      "screenings": [
        {
          "start_time": "11:30",
          "end_time": "13:20",
          "screen": "シアター１３",
          "format": "2D",
          "language": "字幕",
          "availability": "unknown"
        }
      ]
    },
    {
      "title": "幕末ヒポクラテスたち",
      "duration_min": 103,
      "screenings": [
        {
          "start_time": "10:50",
          "end_time": "12:45",
          "screen": "シアター２",
          "format": "2D",
          "language": "日本語",
          "availability": "unknown"
        },
        {
          "start_time": "15:15",
          "end_time": "17:10",
          "screen": "シアター２",
          "format": "2D",
          "language": "日本語",
          "availability": "unknown"
        },
        {
          "start_time": "20:15",
          "end_time": "22:10",
          "screen": "シアター４",
          "format": "2D",
          "language": "日本語",
          "availability": "unknown"
        }
      ]
    },
    {
      "title": "未来(PG12)",
      "duration_min": 130,
      "screenings": [
        {
          "start_time": "08:50",
          "end_time": "11:10",
          "screen": "シアター１１",
          "format": "2D",
          "language": "日本語",
          "availability": "unknown"
        },
        {
          "start_time": "13:20",
          "end_time": "15:40",
          "screen": "シアター１０",
          "format": "2D",
          "language": "日本語",
          "availability": "unknown"
        },
        {
          "start_time": "18:10",
          "end_time": "20:30",
          "screen": "シアター３",
          "format": "2D",
          "language": "日本語",
          "availability": "unknown"
        }
      ]
    },
    {
      "title": "【3D】ビリー・アイリッシュ - HIT ME HARD AND SOFT : THE TOUR (LIVE IN 3D",
      "duration_min": 117,
      "screenings": [
        {
          "start_time": "10:50",
          "end_time": "13:00",
          "screen": "シアター５",
          "format": "2D",
          "language": "日本語",
          "availability": "unknown"
        },
        {
          "start_time": "16:00",
          "end_time": "18:10",
          "screen": "シアター５",
          "format": "2D",
          "language": "日本語",
          "availability": "unknown"
        }
      ]
    },
    {
      "title": "【2D】ビリー・アイリッシュ - HIT ME HARD AND SOFT : THE TOUR (LIVE IN 3D",
      "duration_min": 117,
      "screenings": [
        {
          "start_time": "13:25",
          "end_time": "15:35",
          "screen": "シアター５",
          "format": "2D",
          "language": "日本語",
          "availability": "unknown"
        },
        {
          "start_time": "18:35",
          "end_time": "20:45",
          "screen": "シアター５",
          "format": "2D",
          "language": "日本語",
          "availability": "unknown"
        }
      ]
    },
    {
      "title": "【SCREENX with DolbyAtmos・字幕】プラダを着た悪魔２",
      "duration_min": 119,
      "screenings": [
        {
          "start_time": "09:05",
          "end_time": "11:15",
          "screen": "シアター１２",
          "format": "ScreenX",
          "language": "字幕",
          "availability": "unknown"
        },
        {
          "start_time": "14:05",
          "end_time": "16:15",
          "screen": "シアター１２",
          "format": "ScreenX",
          "language": "字幕",
          "availability": "unknown"
        }
      ]
    },
    {
      "title": "【字幕】プラダを着た悪魔２",
      "duration_min": 119,
      "screenings": [
        {
          "start_time": "11:05",
          "end_time": "13:15",
          "screen": "シアター１",
          "format": "2D",
          "language": "字幕",
          "availability": "unknown"
        },
        {
          "start_time": "13:35",
          "end_time": "15:45",
          "screen": "シアター１",
          "format": "2D",
          "language": "字幕",
          "availability": "unknown"
        },
        {
          "start_time": "16:05",
          "end_time": "18:15",
          "screen": "シアター１",
          "format": "2D",
          "language": "字幕",
          "availability": "unknown"
        },
        {
          "start_time": "18:35",
          "end_time": "20:45",
          "screen": "シアター１",
          "format": "2D",
          "language": "字幕",
          "availability": "unknown"
        },
        {
          "start_time": "21:05",
          "end_time": "23:15",
          "screen": "シアター１",
          "format": "2D",
          "language": "字幕",
          "availability": "unknown"
        }
      ]
    },
    {
      "title": "【吹替】プラダを着た悪魔２",
      "duration_min": 119,
      "screenings": [
        {
          "start_time": "14:30",
          "end_time": "16:40",
          "screen": "シアター９",
          "format": "2D",
          "language": "吹替",
          "availability": "unknown"
        }
      ]
    },
    {
      "title": "ラプソディ・ラプソディ",
      "duration_min": 106,
      "screenings": [
        {
          "start_time": "11:05",
          "end_time": "13:00",
          "screen": "シアター１０",
          "format": "2D",
          "language": "日本語",
          "availability": "unknown"
        },
        {
          "start_time": "16:00",
          "end_time": "17:55",
          "screen": "シアター１０",
          "format": "2D",
          "language": "日本語",
          "availability": "unknown"
        }
      ]
    },
    {
      "title": "【字幕】サンキュー、チャック",
      "duration_min": 111,
      "screenings": [
        {
          "start_time": "08:45",
          "end_time": "10:45",
          "screen": "シアター３",
          "format": "2D",
          "language": "字幕",
          "availability": "unknown"
        },
        {
          "start_time": "15:50",
          "end_time": "17:50",
          "screen": "シアター３",
          "format": "2D",
          "language": "字幕",
          "availability": "unknown"
        }
      ]
    },
    {
      "title": "アギトー超能力戦争ー(PG12)",
      "duration_min": 97,
      "screenings": [
        {
          "start_time": "08:40",
          "end_time": "10:30",
          "screen": "シアター２",
          "format": "2D",
          "language": "日本語",
          "availability": "unknown"
        },
        {
          "start_time": "13:05",
          "end_time": "14:55",
          "screen": "シアター２",
          "format": "2D",
          "language": "日本語",
          "availability": "unknown"
        },
        {
          "start_time": "19:15",
          "end_time": "21:05",
          "screen": "シアター２",
          "format": "2D",
          "language": "日本語",
          "availability": "unknown"
        }
      ]
    },
    {
      "title": "【SCREENX with DolbyAtmos】SAKAMOTO DAYS",
      "duration_min": 128,
      "screenings": [
        {
          "start_time": "19:00",
          "end_time": "21:20",
          "screen": "シアター１２",
          "format": "ScreenX",
          "language": "日本語",
          "availability": "unknown"
        }
      ]
    },
    {
      "title": "【IMAX】SAKAMOTO DAYS",
      "duration_min": 128,
      "screenings": [
        {
          "start_time": "16:30",
          "end_time": "18:50",
          "screen": "シアター７",
          "format": "IMAX",
          "language": "日本語",
          "availability": "unknown"
        },
        {
          "start_time": "21:35",
          "end_time": "23:55",
          "screen": "シアター７",
          "format": "IMAX",
          "language": "日本語",
          "availability": "unknown"
        }
      ]
    },
    {
      "title": "SAKAMOTO DAYS",
      "duration_min": 128,
      "screenings": [
        {
          "start_time": "08:50",
          "end_time": "11:10",
          "screen": "シアター８",
          "format": "2D",
          "language": "日本語",
          "availability": "unknown"
        },
        {
          "start_time": "13:50",
          "end_time": "16:10",
          "screen": "シアター８",
          "format": "2D",
          "language": "日本語",
          "availability": "unknown"
        }
      ]
    },
    {
      "title": "【SCREENX with DolbyAtmos・日本語版】ザ・スーパーマリオギャラクシー・ムービー",
      "duration_min": 99,
      "screenings": [
        {
          "start_time": "21:35",
          "end_time": "23:30",
          "screen": "シアター１２",
          "format": "ScreenX",
          "language": "日本語",
          "availability": "unknown"
        }
      ]
    },
    {
      "title": "【IMAX・日本語版】ザ・スーパーマリオギャラクシー・ムービー",
      "duration_min": 99,
      "screenings": [
        {
          "start_time": "11:45",
          "end_time": "13:40",
          "screen": "シアター７",
          "format": "IMAX",
          "language": "日本語",
          "availability": "unknown"
        }
      ]
    },
    {
      "title": "【2D字幕】ザ・スーパーマリオギャラクシー・ムービー",
      "duration_min": 99,
      "screenings": [
        {
          "start_time": "18:00",
          "end_time": "19:55",
          "screen": "シアター４",
          "format": "2D",
          "language": "字幕",
          "availability": "unknown"
        }
      ]
    },
    {
      "title": "【2D日本語版】ザ・スーパーマリオギャラクシー・ムービー",
      "duration_min": 99,
      "screenings": [
        {
          "start_time": "11:15",
          "end_time": "13:10",
          "screen": "シアター４",
          "format": "2D",
          "language": "日本語",
          "availability": "unknown"
        },
        {
          "start_time": "13:30",
          "end_time": "15:25",
          "screen": "シアター４",
          "format": "2D",
          "language": "日本語",
          "availability": "unknown"
        },
        {
          "start_time": "15:45",
          "end_time": "17:40",
          "screen": "シアター４",
          "format": "2D",
          "language": "日本語",
          "availability": "unknown"
        }
      ]
    },
    {
      "title": "最終楽章 響け！ユーフォニアム　前編",
      "duration_min": 120,
      "screenings": [
        {
          "start_time": "08:35",
          "end_time": "10:45",
          "screen": "シアター１",
          "format": "2D",
          "language": "日本語",
          "availability": "unknown"
        },
        {
          "start_time": "18:50",
          "end_time": "21:00",
          "screen": "シアター８",
          "format": "2D",
          "language": "日本語",
          "availability": "unknown"
        }
      ]
    },
    {
      "title": "【字幕】白い車に乗った女",
      "duration_min": 108,
      "screenings": [
        {
          "start_time": "11:05",
          "end_time": "13:05",
          "screen": "シアター３",
          "format": "2D",
          "language": "字幕",
          "availability": "unknown"
        }
      ]
    },
    {
      "title": "人はなぜラブレターを書くのか",
      "duration_min": 122,
      "screenings": [
        {
          "start_time": "16:00",
          "end_time": "18:10",
          "screen": "シアター１３",
          "format": "2D",
          "language": "日本語",
          "availability": "unknown"
        }
      ]
    },
    {
      "title": "【日本語字幕付】人はなぜラブレターを書くのか",
      "duration_min": 122,
      "screenings": [
        {
          "start_time": "09:00",
          "end_time": "11:10",
          "screen": "シアター１３",
          "format": "2D",
          "language": "字幕",
          "availability": "unknown"
        }
      ]
    },
    {
      "title": "【日本語字幕付】ONE OK ROCK DETOX JAPAN TOUR 2025 IN CINEMAS",
      "duration_min": 117,
      "screenings": [
        {
          "start_time": "08:30",
          "end_time": "10:40",
          "screen": "シアター９",
          "format": "2D",
          "language": "字幕",
          "availability": "unknown"
        }
      ]
    },
    {
      "title": "【SCREENX】名探偵コナン ハイウェイの堕天使",
      "duration_min": 113,
      "screenings": [
        {
          "start_time": "11:35",
          "end_time": "13:40",
          "screen": "シアター１２",
          "format": "ScreenX",
          "language": "日本語",
          "availability": "unknown"
        },
        {
          "start_time": "16:35",
          "end_time": "18:40",
          "screen": "シアター１２",
          "format": "ScreenX",
          "language": "日本語",
          "availability": "unknown"
        }
      ]
    },
    {
      "title": "【IMAX】名探偵コナン ハイウェイの堕天使",
      "duration_min": 113,
      "screenings": [
        {
          "start_time": "09:15",
          "end_time": "11:20",
          "screen": "シアター７",
          "format": "IMAX",
          "language": "日本語",
          "availability": "unknown"
        },
        {
          "start_time": "14:05",
          "end_time": "16:10",
          "screen": "シアター７",
          "format": "IMAX",
          "language": "日本語",
          "availability": "unknown"
        },
        {
          "start_time": "19:10",
          "end_time": "21:15",
          "screen": "シアター７",
          "format": "IMAX",
          "language": "日本語",
          "availability": "unknown"
        }
      ]
    },
    {
      "title": "名探偵コナン ハイウェイの堕天使",
      "duration_min": 113,
      "screenings": [
        {
          "start_time": "11:00",
          "end_time": "13:05",
          "screen": "シアター６",
          "format": "2D",
          "language": "日本語",
          "availability": "unknown"
        },
        {
          "start_time": "13:30",
          "end_time": "15:35",
          "screen": "シアター６",
          "format": "2D",
          "language": "日本語",
          "availability": "unknown"
        },
        {
          "start_time": "16:00",
          "end_time": "18:05",
          "screen": "シアター６",
          "format": "2D",
          "language": "日本語",
          "availability": "unknown"
        },
        {
          "start_time": "21:25",
          "end_time": "23:30",
          "screen": "シアター６",
          "format": "2D",
          "language": "日本語",
          "availability": "unknown"
        }
      ]
    },
    {
      "title": "【字幕】プロジェクト・ヘイル・メアリー",
      "duration_min": 157,
      "screenings": [
        {
          "start_time": "18:15",
          "end_time": "21:05",
          "screen": "シアター１１",
          "format": "2D",
          "language": "字幕",
          "availability": "unknown"
        }
      ]
    },
    {
      "title": "ゴールデンカムイ 網走監獄襲撃編(PG12)",
      "duration_min": 122,
      "screenings": [
        {
          "start_time": "20:45",
          "end_time": "23:00",
          "screen": "シアター１０",
          "format": "2D",
          "language": "日本語",
          "availability": "unknown"
        }
      ]
    },
    {
      "title": "映画ドラえもん 新・のび太の海底鬼岩城",
      "duration_min": 102,
      "screenings": [
        {
          "start_time": "08:40",
          "end_time": "10:35",
          "screen": "シアター５",
          "format": "2D",
          "language": "日本語",
          "availability": "unknown"
        }
      ]
    },
    {
      "title": "木挽町のあだ討ち",
      "duration_min": 120,
      "screenings": [
        {
          "start_time": "08:35",
          "end_time": "10:45",
          "screen": "シアター６",
          "format": "2D",
          "language": "日本語",
          "availability": "unknown"
        }
      ]
    },
    {
      "title": "ほどなく、お別れです",
      "duration_min": 125,
      "screenings": [
        {
          "start_time": "21:10",
          "end_time": "23:25",
          "screen": "シアター５",
          "format": "2D",
          "language": "日本語",
          "availability": "unknown"
        }
      ]
    },
    {
      "title": "超かぐや姫！",
      "duration_min": 145,
      "screenings": [
        {
          "start_time": "18:30",
          "end_time": "21:05",
          "screen": "シアター６",
          "format": "2D",
          "language": "日本語",
          "availability": "unknown"
        }
      ]
    },
    {
      "title": "【SCREENX with DolbyAtmos・字幕】プラダを着た悪魔２",
      "duration_min": 119,
      "screenings": []
    },
    {
      "title": "ゴールデンカムイ 網走監獄襲撃編(PG12)",
      "duration_min": 122,
      "screenings": []
    },
    {
      "title": "名探偵コナン ハイウェイの堕天使",
      "duration_min": 113,
      "screenings": []
    },
    {
      "title": "ほどなく、お別れです",
      "duration_min": 125,
      "screenings": []
    },
    {
      "title": "ラプソディ・ラプソディ",
      "duration_min": 106,
      "screenings": []
    },
    {
      "title": "鬼の花嫁",
      "duration_min": 122,
      "screenings": []
    },
    {
      "title": "映画 えんとつ町のプペル ～約束の時計台～",
      "duration_min": 99,
      "screenings": []
    },
    {
      "title": "【限界突破(リミットブレイク)応援上映!】名探偵コナン ハイウェイの堕天使",
      "duration_min": 113,
      "screenings": [
        {
          "start_time": "19:00",
          "end_time": "21:05",
          "screen": "シアター１",
          "format": "2D",
          "language": "日本語",
          "availability": "available"
        }
      ]
    },
    {
      "title": "【初日舞台挨拶中継】映画 ラブライブ！蓮ノ空女学院スクールアイドルクラブ Bloom Garden Party",
      "duration_min": 120,
      "screenings": [
        {
          "start_time": "16:45",
          "end_time": "18:55",
          "screen": "シアター１",
          "format": "2D",
          "language": "日本語",
          "availability": "available"
        },
        {
          "start_time": "19:40",
          "end_time": "21:35",
          "screen": "シアター１",
          "format": "2D",
          "language": "日本語",
          "availability": "available"
        }
      ]
    },
    {
      "title": "【発声可能上映】ONE OK ROCK DETOX JAPAN TOUR 2025 IN CINEMAS",
      "duration_min": 117,
      "screenings": [
        {
          "start_time": "19:00",
          "end_time": "21:10",
          "screen": "シアター６",
          "format": "2D",
          "language": "日本語",
          "availability": "available"
        }
      ]
    }
  ],
  "scraped_at": "2026-05-06T12:24:00.012827"
}